sorrydb/__init__.py
sorrydb/agents/__init__.py
sorrydb/agents/json_agent.py
sorrydb/agents/llm_strategy.py
sorrydb/agents/rfl_strategy.py
sorrydb/cli/deduplicate_db.py
sorrydb/cli/init_db.py
sorrydb/cli/run_llm_agent.py
sorrydb/cli/run_rfl_agent.py
sorrydb/cli/scrape_reservoir.py
sorrydb/cli/settings.py
sorrydb/cli/sorrydb_cli.py
sorrydb/cli/update_db.py
sorrydb/database/__init__.py
sorrydb/database/build_database.py
sorrydb/database/deduplicate_database.py
sorrydb/database/process_sorries.py
sorrydb/database/reservoir.py
sorrydb/database/sorry.py
sorrydb/database/sorry_database.py
sorrydb/utils/__init__.py
sorrydb/utils/git_ops.py
sorrydb/utils/lean_repo.py
sorrydb/utils/repl_ops.py
sorrydb/utils/verify.py
sorrydb-0.1.1.dist-info/LICENSE
sorrydb-0.1.1.dist-info/METADATA
sorrydb-0.1.1.dist-info/WHEEL
sorrydb-0.1.1.dist-info/entry_points.txt
sorrydb-0.1.1.dist-info/RECORD
