Metadata-Version: 2.3
Name: sorrydb
Version: 0.1.1
Summary: Build a continously updating database of sorry statements in public Lean4 repositories
License: Apache-2.0
Author: Lenny Taelman
Author-email: l.d.j.taelman@uva.nl
Requires-Python: >=3.11,<3.14
Classifier: License :: OSI Approved :: Apache Software License
Classifier: Programming Language :: Python :: 3
Classifier: Programming Language :: Python :: 3.11
Classifier: Programming Language :: Python :: 3.12
Classifier: Programming Language :: Python :: 3.13
Requires-Dist: dotenv (>=0.9.9,<0.10.0)
Requires-Dist: gitpython (>=3.1.44,<4.0.0)
Requires-Dist: langchain (>=0.3.20,<0.4.0)
Requires-Dist: langchain-anthropic (>=0.3.10,<0.4.0)
Requires-Dist: langchain-google-genai (>=2.1.0,<3.0.0)
Requires-Dist: langchain-openai (>=0.3.8,<0.4.0)
Requires-Dist: pydantic-settings (>=2.9.1,<3.0.0)
Requires-Dist: requests (>=2.32.3,<3.0.0)
Requires-Dist: typer (>=0.15.3,<0.16.0)
